troppo/__init__.py
troppo/methods_wrappers.py
troppo/methods/__init__.py
troppo/methods/base.py
troppo/methods/gapfill/__init__.py
troppo/methods/gapfill/consensus.py
troppo/methods/gapfill/efm.py
troppo/methods/gapfill/fastcc.py
troppo/methods/gapfill/pathway_analysis.py
troppo/methods/reconstruction/__init__.py
troppo/methods/reconstruction/corda.py
troppo/methods/reconstruction/fastcore.py
troppo/methods/reconstruction/gimme.py
troppo/methods/reconstruction/imat.py
troppo/methods/reconstruction/mba.py
troppo/methods/reconstruction/swiftcore.py
troppo/methods/reconstruction/tINIT.py
troppo/omics/__init__.py
troppo/omics/core.py
troppo/omics/gene_level_thresholding.py
troppo/omics/id_converter.py
troppo/omics/integration.py
troppo/omics/readers/__init__.py
troppo/omics/readers/generic.py
troppo/omics/readers/hpa.py
troppo/omics/readers/microarray.py
troppo/tasks/__init__.py
troppo/tasks/core.py
troppo/tasks/task_io.py
troppo/utilities/__init__.py
troppo/utilities/list.py
troppo/utilities/statistics.py
troppo/validation/__init__.py
troppo/validation/core.py
utilities/__init__.py
utilities/extra_information.py
utilities/task.py
troppo-0.0.7.dist-info/LICENSE.txt
troppo-0.0.7.dist-info/METADATA
troppo-0.0.7.dist-info/WHEEL
troppo-0.0.7.dist-info/top_level.txt
troppo-0.0.7.dist-info/RECORD
