Metadata-Version: 2.1
Name: troppo
Version: 0.0.7
Summary: TROPPO - Tissue-specific RecOnstruction and Phenotype Prediction using Omics data
Home-page: https://github.com/BioSystemsUM/troppo
Author: Jorge Ferreira & Vítor Vieira
Author-email: jorge.ferreira@ceb.uminho.pt
License: GNU General Public License v3.0
Keywords: pathway analysis metabolic model
Platform: UNKNOWN
Classifier: Development Status :: 4 - Beta
Classifier: Topic :: Scientific/Engineering :: Bio-Informatics
Classifier: Intended Audience :: Science/Research
Classifier: Programming Language :: Python :: 3.5
Classifier: License :: OSI Approved :: GNU General Public License v3 (GPLv3)
Classifier: Topic :: Software Development :: Libraries :: Python Modules
License-File: LICENSE.txt
Requires-Dist: cobamp (==0.2.1)
